{
        "results_count": 10,
        "results": [
                {
                        "title": "[HTML][HTML] The Circadian-clock Regulates the Gravitropic Response",
                        "title_link": "https://sciendo.com/es/article/10.2478/gsr-2021-0014",
                        "publication_info": "JS Tolsma, KT Ryan, JJ Torres, JT Richards\u2026\u00a0- \u2026\u00a0and Space Research, 2021 - sciendo.com",
                        "snippet": "\u2026 responses were affected by simulated microgravity. Ground-based microgravity simulators \nprovide cost-effective means to study how microgravity affects plant growth and development. \u2026",
                        "citations": 2,
                        "cited_by": "https://scholar.google.com/scholar?cites=11988481100508936886&as_sdt=2005&sciodt=0,5&hl=en",
                        "related_articles": "https://scholar.google.com/scholar?q=related:trpREAukX6YJ:scholar.google.com/&scioq=microgravity+space+biology&hl=en&as_sdt=0,5&as_ylo=2021&as_yhi=2021",
                        "all_article_versions": "https://scholar.google.com/scholar?cluster=11988481100508936886&hl=en&as_sdt=0,5&as_ylo=2021&as_yhi=2021"
                },
                {
                        "title": "[HTML][HTML] Mechanical force-driven TNF\u03b1 endocytosis governs stem cell homeostasis",
                        "title_link": "https://www.nature.com/articles/s41413-020-00117-x",
                        "publication_info": "W Yu, C Chen, X Kou, B Sui, T Yu, D Liu, R Wang\u2026\u00a0- Bone Research, 2021 - nature.com",
                        "snippet": "\u2026 role in regulating a variety of biological processes, not only \u2026 and in the bone marrow space, \nresulting in resident MSC \u2026 are exposed to microgravity during space missions. However\u2026",
                        "citations": 7,
                        "cited_by": "https://scholar.google.com/scholar?cites=5611710161961908940&as_sdt=2005&sciodt=0,5&hl=en",
                        "related_articles": "https://scholar.google.com/scholar?q=related:zHowAqnM4E0J:scholar.google.com/&scioq=microgravity+space+biology&hl=en&as_sdt=0,5&as_ylo=2021&as_yhi=2021",
                        "all_article_versions": "https://scholar.google.com/scholar?cluster=5611710161961908940&hl=en&as_sdt=0,5&as_ylo=2021&as_yhi=2021"
                },
                {
                        "title": "[PDF][PDF] Topical: Low and Intermediate Temperature Chemistry in Cool and Warm Flames Primary author",
                        "title_link": "http://surveygizmoresponseuploads.s3.amazonaws.com/fileuploads/623127/6378869/87-546f14ac3aa227d1eebe5a349a16eb6c_BelmontEricaL.pdf",
                        "publication_info": "E Belmont, D Dietrich, T Farouk, V Nayagam, P Ronney\u2026 - \u2026\u00a0.s3.amazonaws.com",
                        "snippet": "\u2026 A major distinction of combustion in microgravity versus \u2026 Future fuels are likely to include \nincreasing amounts of bio-\u2026 space travel. The demonstrated potential for sustained cool flames in \u2026",
                        "citations": 0,
                        "cited_by": "https://scholar.google.com/scholar?q=related:0HRjo00ekPMJ:scholar.google.com/&scioq=microgravity+space+biology&hl=en&as_sdt=0,5&as_ylo=2021&as_yhi=2021",
                        "related_articles": "https://scholar.google.comjavascript:void(0)",
                        "all_article_versions": "https://scholar.google.comNone"
                },
                {
                        "title": "How certain are we? Development of an ensemble based framework for assessing astronaut cancer risks from space radiation",
                        "title_link": "https://www.biorxiv.org/content/10.1101/2021.01.29.428854.abstract",
                        "publication_info": "LC Simonsen, TC Slaba\u00a0- bioRxiv, 2021 - biorxiv.org",
                        "snippet": "\u2026 the fact that biological effects of the primary and secondary space \u2026 from space radiation impart \nunique biological damage to \u2026 stressors (such as, micro-gravity, isolation, confinement, and \u2026",
                        "citations": 0,
                        "cited_by": "https://scholar.google.com/scholar?q=related:1TV3HFsbya4J:scholar.google.com/&scioq=microgravity+space+biology&hl=en&as_sdt=0,5&as_ylo=2021&as_yhi=2021",
                        "related_articles": "https://scholar.google.com/scholar?cluster=12594627911051851221&hl=en&as_sdt=0,5&as_ylo=2021&as_yhi=2021",
                        "all_article_versions": "https://scholar.google.com/scholar?cluster=12594627911051851221&hl=en&as_sdt=0,5&as_ylo=2021&as_yhi=2021"
                },
                {
                        "title": "Moonwalking: When other worlds belong to women",
                        "title_link": "https://search.informit.org/doi/abs/10.3316/INFORMIT.145797332531733",
                        "publication_info": "A Gorman\u00a0- Griffith REVIEW, 2021 - search.informit.org",
                        "snippet": "\u2026 a microgravity space toilet designed with the needs of female crew in mind was installed in \nthe International Space \u2026 biological materials. Then there is the level of decision-making about \u2026",
                        "citations": 1,
                        "cited_by": "https://scholar.google.com/scholar?cites=646803683757631296&as_sdt=2005&sciodt=0,5&hl=en",
                        "related_articles": "https://scholar.google.com/scholar?q=related:QKfJAYbo-QgJ:scholar.google.com/&scioq=microgravity+space+biology&hl=en&as_sdt=0,5&as_ylo=2021&as_yhi=2021",
                        "all_article_versions": "https://scholar.google.com/scholar?cluster=646803683757631296&hl=en&as_sdt=0,5&as_ylo=2021&as_yhi=2021"
                },
                {
                        "title": "Shotgun metagenomic analysis of kombucha mutualistic community exposed to Mars\u2010like environment outside the International Space Station",
                        "title_link": "https://sfamjournals.onlinelibrary.wiley.com/doi/abs/10.1111/1462-2920.15405",
                        "publication_info": "A G\u00f3es\u2010Neto, O Kukharenko, I Orlovska\u2026\u00a0- Environmental\u00a0\u2026, 2021 - Wiley Online Library",
                        "snippet": "\u2026 exposed to the space/Mars-like environment outside the International Space Station in order \n\u2026 Our study revealed that the long-term exposure to space/Mars-like conditions on low Earth \u2026",
                        "citations": 18,
                        "cited_by": "https://scholar.google.com/scholar?cites=8338670137807632715&as_sdt=2005&sciodt=0,5&hl=en",
                        "related_articles": "https://scholar.google.com/scholar?q=related:S3kuZ0_ouHMJ:scholar.google.com/&scioq=microgravity+space+biology&hl=en&as_sdt=0,5&as_ylo=2021&as_yhi=2021",
                        "all_article_versions": "https://scholar.google.com/scholar?cluster=8338670137807632715&hl=en&as_sdt=0,5&as_ylo=2021&as_yhi=2021"
                },
                {
                        "title": "Feeling Through Spacesuits: Application of Space-Resilient E-Textiles to Enable Haptic Feedback on Pressurized Extravehicular Suits",
                        "title_link": "https://ieeexplore.ieee.org/abstract/document/9438515/",
                        "publication_info": "S Payra, I Wicaksono, J Cherston\u2026\u00a0- 2021 IEEE\u00a0\u2026, 2021 - ieeexplore.ieee.org",
                        "snippet": "\u2026 \u2019s Wearable Technology lab have studied strain sensors and other internal biological sensors \nto improve spacesuit fit and monitor human health in microgravity [18], [19]. Both ESA and \u2026",
                        "citations": 0,
                        "cited_by": "https://scholar.google.com/scholar?q=related:blPE4IzPmO0J:scholar.google.com/&scioq=microgravity+space+biology&hl=en&as_sdt=0,5&as_ylo=2021&as_yhi=2021",
                        "related_articles": "https://scholar.google.com/scholar?cluster=17120662187422274414&hl=en&as_sdt=0,5&as_ylo=2021&as_yhi=2021",
                        "all_article_versions": "https://scholar.google.com/scholar?cluster=17120662187422274414&hl=en&as_sdt=0,5&as_ylo=2021&as_yhi=2021"
                },
                {
                        "title": "[PDF][PDF] Investigating the Effects of Gravity on the Genetic Regulation of Human Telomeres",
                        "title_link": "https://www.researchgate.net/profile/Erin-Richardson-5/publication/364386997_Investigating_the_Effects_of_Gravity_on_the_Genetic_Regulation_of_Human_Telomeres/links/6350fc958d4484154a1a81f3/Investigating-the-Effects-of-Gravity-on-the-Genetic-Regulation-of-Human-Telomeres.pdf",
                        "publication_info": "A Piro, T Peters, MK Campbell, E Richardson, D Matic\u2026 - 2021 - researchgate.net",
                        "snippet": "\u2026 flight to isolate the microgravity variable and understand its \u2026 twelve time sensitive samples \nin biological triplicates. The system \u2026 the course of a year in space. There are several factors in \u2026",
                        "citations": 0,
                        "cited_by": "https://scholar.google.comjavascript:void(0)",
                        "related_articles": "https://scholar.google.comhttps://scholar.googleusercontent.com/scholar?q=cache:kARaKtUtDdYJ:scholar.google.com/+microgravity+space+biology&hl=en&as_sdt=0,5&as_ylo=2021&as_yhi=2021",
                        "all_article_versions": "https://scholar.google.comNone"
                },
                {
                        "title": "Microbial interaction with terrestrial and extraterrestrial rocks on the International Space Station",
                        "title_link": "https://elib.dlr.de/143936/",
                        "publication_info": "R Santomartino, CS Cockell, AC Waajen, W de Wit\u2026 - 2021 - elib.dlr.de",
                        "snippet": "\u2026 weeks in microgravity, simulated \u2026 in space, by investigating the interaction of S. desiccabilis \nand the fungus Penicillium simplicissimum with meteorite rock (L-chondrite) in microgravity \u2026",
                        "citations": 0,
                        "cited_by": "https://scholar.google.com/scholar?q=related:lOABU5fFmckJ:scholar.google.com/&scioq=microgravity+space+biology&hl=en&as_sdt=0,5&as_ylo=2021&as_yhi=2021",
                        "related_articles": "https://scholar.google.comjavascript:void(0)",
                        "all_article_versions": "https://scholar.google.comNone"
                },
                {
                        "title": "Improving astronaut cancer risk assessment from space radiation with an ensemble model framework",
                        "title_link": "https://www.sciencedirect.com/science/article/pii/S221455242100047X",
                        "publication_info": "LC Simonsen, TC Slaba\u00a0- Life Sciences in Space Research, 2021 - Elsevier",
                        "snippet": "\u2026 the fact that biological effects of the primary and secondary space radiation environment \u2026 \nto a multitude of spaceflight stressors (such as, micro-gravity, isolation, confinement, and sleep \u2026",
                        "citations": 8,
                        "cited_by": "https://scholar.google.com/scholar?cites=9506906298272573589&as_sdt=2005&sciodt=0,5&hl=en",
                        "related_articles": "https://scholar.google.com/scholar?q=related:leh1lehQ74MJ:scholar.google.com/&scioq=microgravity+space+biology&hl=en&as_sdt=0,5&as_ylo=2021&as_yhi=2021",
                        "all_article_versions": "https://scholar.google.com/scholar?cluster=9506906298272573589&hl=en&as_sdt=0,5&as_ylo=2021&as_yhi=2021"
                }
        ]
}