{
        "results_count": 10,
        "results": [
                {
                        "title": "The state of the art of Piezo1 channels in skeletal muscle regeneration",
                        "title_link": "https://www.mdpi.com/1676724",
                        "publication_info": "A Bernareggi, A Bosutti, G Massaria\u2026\u00a0- International Journal of\u00a0\u2026, 2022 - mdpi.com",
                        "snippet": "\u2026 into signalling events that elicit biological responses. The main \u2026 when cultured in simulated \nmicrogravity conditions [76]. \u2026 effects of microgravity during prolonged space flights and in the \u2026",
                        "citations": 1,
                        "cited_by": "https://scholar.google.com/scholar?cites=4593689767561183230&as_sdt=2005&sciodt=0,5&hl=en",
                        "related_articles": "https://scholar.google.com/scholar?cluster=4593689767561183230&hl=en&as_sdt=0,5&as_ylo=2022&as_yhi=2022",
                        "all_article_versions": "https://scholar.google.com/scholar?cluster=4593689767561183230&hl=en&as_sdt=0,5&as_ylo=2022&as_yhi=2022"
                },
                {
                        "title": "[HTML][HTML] Analysing bio-art's epistemic landscape: from metaphoric to post-metaphoric structure",
                        "title_link": "https://link.springer.com/article/10.1057/s41292-022-00270-y",
                        "publication_info": "DAM Ahmedien\u00a0- BioSocieties, 2022 - Springer",
                        "snippet": "\u2026 structure could be a powerful joint space for artists and biologists when the metaphor\u2019s \u2026 \nThe scaffold was seeded with living cells and the ear was cultured in a rotating micro-gravity \u2026",
                        "citations": 0,
                        "cited_by": "https://scholar.google.com/scholar?q=related:4Bn4jx2RIxoJ:scholar.google.com/&scioq=microgravity+space+biology&hl=en&as_sdt=0,5&as_ylo=2022&as_yhi=2022",
                        "related_articles": "https://scholar.google.comjavascript:void(0)",
                        "all_article_versions": "https://scholar.google.comNone"
                },
                {
                        "title": "Balance between the cell viability and death in 3D",
                        "title_link": "https://www.sciencedirect.com/science/article/pii/S1084952122002671",
                        "publication_info": "AC Debruyne, IA Okkelman, RI Dmitriev\u00a0- \u2026\u00a0in Cell & Developmental Biology, 2022 - Elsevier",
                        "snippet": "\u2026 Collectively, 3D in vitro models can recapitulate many biological phenomena of cell viability \nand death in three-dimensional context(s) at different levels of complexity and within a more \u2026",
                        "citations": 1,
                        "cited_by": "https://scholar.google.com/scholar?cites=18233080977727282680&as_sdt=2005&sciodt=0,5&hl=en",
                        "related_articles": "https://scholar.google.com/scholar?cluster=18233080977727282680&hl=en&as_sdt=0,5&as_ylo=2022&as_yhi=2022",
                        "all_article_versions": "https://scholar.google.com/scholar?cluster=18233080977727282680&hl=en&as_sdt=0,5&as_ylo=2022&as_yhi=2022"
                },
                {
                        "title": "Cybernetics as a conversation with the Cosmos",
                        "title_link": "https://www.sciencedirect.com/science/article/pii/S0079610722000360",
                        "publication_info": "JS Torday\u00a0- Progress in Biophysics and Molecular Biology, 2022 - Elsevier",
                        "snippet": "\u2026 , the cell-cell communication mediated by soluble growth factors and their receptors highlighted \nin this article recognizes our \u2018history\u2019, offering the possibility of transcending space-time \u2026",
                        "citations": 1,
                        "cited_by": "https://scholar.google.com/scholar?cites=5357583598523685003&as_sdt=2005&sciodt=0,5&hl=en",
                        "related_articles": "https://scholar.google.com/scholar?q=related:i5h2rOX1WUoJ:scholar.google.com/&scioq=microgravity+space+biology&hl=en&as_sdt=0,5&as_ylo=2022&as_yhi=2022",
                        "all_article_versions": "https://scholar.google.com/scholar?cluster=5357583598523685003&hl=en&as_sdt=0,5&as_ylo=2022&as_yhi=2022"
                },
                {
                        "title": "An Overview of Ground-Based Electrostatic Levitation",
                        "title_link": "https://link.springer.com/chapter/10.1007/978-3-030-89784-0_10",
                        "publication_info": "MP SanSoucie\u00a0- Metallurgy in Space, 2022 - Springer",
                        "snippet": "\u2026 These limitations necessitate levitation facilities in microgravity. For these reasons, and \nothers, the European Space Agency (ESA) developed the International Space Station \u2026",
                        "citations": 1,
                        "cited_by": "https://scholar.google.com/scholar?cites=4910770114962929151&as_sdt=2005&sciodt=0,5&hl=en",
                        "related_articles": "https://scholar.google.com/scholar?q=related:_zX4s2aPJkQJ:scholar.google.com/&scioq=microgravity+space+biology&hl=en&as_sdt=0,5&as_ylo=2022&as_yhi=2022",
                        "all_article_versions": "https://scholar.google.com/scholar?cluster=4910770114962929151&hl=en&as_sdt=0,5&as_ylo=2022&as_yhi=2022"
                },
                {
                        "title": "[PDF][PDF] Environment initial focus of business, law, economics center",
                        "title_link": "https://digitalcommons.wustl.edu/cgi/viewcontent.cgi?article=1549&context=record",
                        "publication_info": "W Vernon, MK Piper - digitalcommons.wustl.edu",
                        "snippet": "\u2026 the effects of microgravity \u2014 the weak gravitational field found in outer space \u2014 on germination \n\u2026 And this past summer she worked at the University of Kansas biology department in the \u2026",
                        "citations": 0,
                        "cited_by": "https://scholar.google.com/scholar?q=related:RkY0pWkNIBYJ:scholar.google.com/&scioq=microgravity+space+biology&hl=en&as_sdt=0,5&as_ylo=2022&as_yhi=2022",
                        "related_articles": "https://scholar.google.comjavascript:void(0)",
                        "all_article_versions": "https://scholar.google.comNone"
                },
                {
                        "title": "HIF-1\u03b1 mediates osteoclast-induced disuse osteoporosis via cytoophidia in the femur of mice",
                        "title_link": "https://www.sciencedirect.com/science/article/pii/S8756328222003258",
                        "publication_info": "M Bie, Y Tang, Y Xia, Q Zhang, Y Tian, C Cheng, X Li\u2026\u00a0- Bone, 2022 - Elsevier",
                        "snippet": "\u2026 immobilization, bed rest and a microgravity environment in space, is becoming more common \nin \u2026 However, the biological significance and underlying mechanism of IMPDH and CTPS \u2026",
                        "citations": 0,
                        "cited_by": "https://scholar.google.com/scholar?cluster=10727043811624633773&hl=en&as_sdt=0,5&as_ylo=2022&as_yhi=2022",
                        "related_articles": "https://scholar.google.comjavascript:void(0)",
                        "all_article_versions": "https://scholar.google.com/scholar?cluster=10727043811624633773&hl=en&as_sdt=0,5&as_ylo=2022&as_yhi=2022"
                },
                {
                        "title": "Photosensitized Thermoplastic Nano-Photocatalysts Active in the Visible Light Range for Potential Applications Inside Extraterrestrial Facilities",
                        "title_link": "https://www.mdpi.com/1547564",
                        "publication_info": "L Mezzina, A Nicosia, F Vento, G De Guidi, PG Mineo\u00a0- Nanomaterials, 2022 - mdpi.com",
                        "snippet": "\u2026 However, its use in underground structures and/or microgravity environments (eg, extraterrestrial \n\u2026 Moreover, microgravity does not allow the recovery of the photocatalytic slurry from the \u2026",
                        "citations": 2,
                        "cited_by": "https://scholar.google.com/scholar?cites=7696507527051299033&as_sdt=2005&sciodt=0,5&hl=en",
                        "related_articles": "https://scholar.google.com/scholar?q=related:2UgDadF8z2oJ:scholar.google.com/&scioq=microgravity+space+biology&hl=en&as_sdt=0,5&as_ylo=2022&as_yhi=2022",
                        "all_article_versions": "https://scholar.google.com/scholar?cluster=7696507527051299033&hl=en&as_sdt=0,5&as_ylo=2022&as_yhi=2022"
                },
                {
                        "title": "[HTML][HTML] Comparative analysis of aroma components and quality of Geotrichum candidum after space mutation breeding",
                        "title_link": "https://www.ncbi.nlm.nih.gov/pmc/articles/PMC9354409/",
                        "publication_info": "J Chen, Q Li, J Wang, W Chen, Q Zheng\u2026\u00a0- Frontiers in\u00a0\u2026, 2022 - ncbi.nlm.nih.gov",
                        "snippet": "\u2026 and mutated by utilizing space microgravity mutagenesis breeding, and then \u2026 a biological \npreservative in food. Therefore, mutagenic-type G. candidum had a huge prospect in biological \u2026",
                        "citations": 0,
                        "cited_by": "https://scholar.google.com/scholar?cluster=13944102537147018482&hl=en&as_sdt=0,5&as_ylo=2022&as_yhi=2022",
                        "related_articles": "https://scholar.google.comjavascript:void(0)",
                        "all_article_versions": "https://scholar.google.com/scholar?cluster=13944102537147018482&hl=en&as_sdt=0,5&as_ylo=2022&as_yhi=2022"
                },
                {
                        "title": "[HTML][HTML] Polyvinyl chloride gel based electro-active switchable bio-inspired adhesive",
                        "title_link": "https://www.sciencedirect.com/science/article/pii/S1359835X2200361X",
                        "publication_info": "Q He, H Pan, Z Zhao, H Zhang, G Yin, Y Wu\u2026\u00a0- Composites Part A\u00a0\u2026, 2022 - Elsevier",
                        "snippet": "\u2026 In this work, PVC based electro-active bio-inspired adhesive is successfully fabricated, \nwhich is composed of a PVC active backing layer and a passive PVC fibrillar adhesive layer. As \u2026",
                        "citations": 1,
                        "cited_by": "https://scholar.google.com/scholar?cites=6722838579084261466&as_sdt=2005&sciodt=0,5&hl=en",
                        "related_articles": "https://scholar.google.com/scholar?cluster=6722838579084261466&hl=en&as_sdt=0,5&as_ylo=2022&as_yhi=2022",
                        "all_article_versions": "https://scholar.google.com/scholar?cluster=6722838579084261466&hl=en&as_sdt=0,5&as_ylo=2022&as_yhi=2022"
                }
        ]
}